pyiof/__init__.py
pyiof/base.py
pyiof/class_.py
pyiof/competitor.py
pyiof/contact.py
pyiof/course.py
pyiof/event.py
pyiof/fee.py
pyiof/message_elements.py
pyiof/misc.py
pyiof/result.py
pyiof/start.py
pyiof/xml_base.py
pyiof-0.2.0.dist-info/LICENSE
pyiof-0.2.0.dist-info/METADATA
pyiof-0.2.0.dist-info/WHEEL
pyiof-0.2.0.dist-info/RECORD
