Metadata-Version: 2.3
Name: pyiof
Version: 0.2.0
Summary: Python package for reading / writing IOF datastandard 3.0
Author: Simske
Author-email: mail@simske.com
Requires-Python: >=3.10,<4.0
Classifier: Programming Language :: Python :: 3
Classifier: Programming Language :: Python :: 3.10
Classifier: Programming Language :: Python :: 3.11
Classifier: Programming Language :: Python :: 3.12
Classifier: Programming Language :: Python :: 3.13
Requires-Dist: pydantic-xml[lxml] (>=2.14.1,<3.0.0)
